toolkitplus/__init__.py
toolkitplus/py.typed
toolkitplus-0.1.0rc1.dist-info/WHEEL
toolkitplus-0.1.0rc1.dist-info/METADATA
toolkitplus-0.1.0rc1.dist-info/RECORD
