Metadata-Version: 2.3
Name: toolkitplus
Version: 0.1.0rc1
Summary: Extended Python toolkit
Author: oyghen
Author-email: oyghen <oyghen@duck.com>
Requires-Python: >=3.11
